AEPi/__init__.py
AEPi/codec.py
AEPi/constants.py
AEPi/exceptions.py
AEPi/py.typed
AEPi/codecs/EtcPakCodec.py
AEPi/codecs/RawCodec.py
AEPi/codecs/Tex2ImgCodec.py
AEPi/codecs/__init__.py
AEPi/image/AEI.py
AEPi/image/__init__.py
AEPi/image/texture.py
AEPi/lib/__init__.py
AEPi/lib/binaryio.py
AEPi/lib/imageOps.py
aepi-0.8.4.dist-info/licenses/LICENSE
aepi-0.8.4.dist-info/METADATA
aepi-0.8.4.dist-info/WHEEL
aepi-0.8.4.dist-info/top_level.txt
aepi-0.8.4.dist-info/RECORD
