Metadata-Version: 2.4
Name: AEPi
Version: 0.8.4
Summary: Read and write Abyss Engine Image (AEI) files from python, for Galaxy on Fire 2
Home-page: https://github.com/Trimatix/AEPi
Author: Jasper Law
Author-email: trimatix.music@gmail.com
Project-URL: Bug Tracker, https://github.com/Trimatix/AEPi/issues
Keywords: game,python,galaxy-on-fire,image-compression,image-conversion,game-mod-tool,abyss-engine
Classifier: Programming Language :: Python :: 3.11
Classifier: Programming Language :: Python :: 3.12
Classifier: Programming Language :: Python :: 3.13
Classifier: License :: OSI Approved :: Apache Software License
Classifier: Operating System :: OS Independent
Requires-Python: >=3.6
License-File: LICENSE
Requires-Dist: pillow
Requires-Dist: etcpak>=0.9.13
Requires-Dist: tex2img>=0.9
Provides-Extra: test
Requires-Dist: pytest; extra == "test"
Dynamic: license-file
